mcservstatus/__init__.py
mcservstatus-0.0.1.dist-info/METADATA
mcservstatus-0.0.1.dist-info/WHEEL
mcservstatus-0.0.1.dist-info/top_level.txt
mcservstatus-0.0.1.dist-info/RECORD
