Metadata-Version: 2.1
Name: mcservstatus
Version: 0.0.1
Summary: API wrapper for mcservstat.us
Home-page: https://github.com/Xd-pro/mcservstatuspy
Author: FinnbarM
Author-email: prokitpvp@yandex.com
License: UNKNOWN
Project-URL: Bug Tracker, https://github.com/pypa/sampleproject/issues
Platform: UNKNOWN
Classifier: Programming Language :: Python :: 3
Classifier: License :: OSI Approved :: MIT License
Classifier: Operating System :: OS Independent
Requires-Python: >=3.6
